./flit_install_py2.py
flit_install_py2-0.1.dist-info/METADATA
flit_install_py2-0.1.dist-info/WHEEL
flit_install_py2-0.1.dist-info/entry_points.txt
flit_install_py2-0.1.dist-info/RECORD
