Metadata-Version: 1.2
Name: flit_install_py2
Version: 0.1
Summary: Shim to install packages using flit metadata on Python 2
Home-page: https://github.com/takluyver/flit_install_py2
License: UNKNOWN
Author: Thomas Kluyver
Author-email: thomas@kluyver.me.uk
Classifier: License :: OSI Approved :: MIT License
Requires-Dist: configparser
